{"note":"This file is an internal implementation detail to speed up HTML report generation. Its format can change at any time. You might be looking for the JSON report: https://coverage.rtfd.io/cmd.html#cmd-json","format":5,"version":"7.13.1","globals":"31de48086836b582c906a9cec4967234","files":{"z_31b6b07b49f6e852___init___py":{"hash":"38e2ca275efedb1ed327f0e1ad7fd606","index":{"url":"z_31b6b07b49f6e852___init___py.html","file":"src/tmc_driver/__init__.py","description":"","nums":{"precision":0,"n_files":1,"n_statements":17,"n_excluded":0,"n_missing":0,"n_branches":0,"n_partial_branches":0,"n_missing_branches":0}}},"z_31b6b07b49f6e852__tmc_exceptions_py":{"hash":"3c61bc7d54e988002d59208c1d418dac","index":{"url":"z_31b6b07b49f6e852__tmc_exceptions_py.html","file":"src/tmc_driver/_tmc_exceptions.py","description":"","nums":{"precision":0,"n_files":1,"n_statements":5,"n_excluded":0,"n_missing":0,"n_branches":0,"n_partial_branches":0,"n_missing_branches":0}}},"z_31b6b07b49f6e852__tmc_math_py":{"hash":"29f685c76aec0d4dbf6391a22c8aa066","index":{"url":"z_31b6b07b49f6e852__tmc_math_py.html","file":"src/tmc_driver/_tmc_math.py","description":"","nums":{"precision":0,"n_files":1,"n_statements":26,"n_excluded":0,"n_missing":0,"n_branches":0,"n_partial_branches":0,"n_missing_branches":0}}},"z_31b6b07b49f6e852__tmc_stallguard_py":{"hash":"3243ad977f9465475b2a5f8c66e65ad6","index":{"url":"z_31b6b07b49f6e852__tmc_stallguard_py.html","file":"src/tmc_driver/_tmc_stallguard.py","description":"","nums":{"precision":0,"n_files":1,"n_statements":123,"n_excluded":2,"n_missing":23,"n_branches":0,"n_partial_branches":0,"n_missing_branches":0}}},"z_31b6b07b49f6e852__tmc_stepperdriver_py":{"hash":"c61efc4ff4961a0ac47bb99ccce5367b","index":{"url":"z_31b6b07b49f6e852__tmc_stepperdriver_py.html","file":"src/tmc_driver/_tmc_stepperdriver.py","description":"","nums":{"precision":0,"n_files":1,"n_statements":72,"n_excluded":13,"n_missing":10,"n_branches":0,"n_partial_branches":0,"n_missing_branches":0}}},"z_31b6b07b49f6e852__tmc_validation_py":{"hash":"bdf0d9ef46b02de898240ae2caf9ff4d","index":{"url":"z_31b6b07b49f6e852__tmc_validation_py.html","file":"src/tmc_driver/_tmc_validation.py","description":"","nums":{"precision":0,"n_files":1,"n_statements":7,"n_excluded":0,"n_missing":0,"n_branches":0,"n_partial_branches":0,"n_missing_branches":0}}},"z_31b6b07b49f6e852__tmc_xxxx_py":{"hash":"157ddd576f6e597e985eee2bcd61d312","index":{"url":"z_31b6b07b49f6e852__tmc_xxxx_py.html","file":"src/tmc_driver/_tmc_xxxx.py","description":"","nums":{"precision":0,"n_files":1,"n_statements":175,"n_excluded":22,"n_missing":52,"n_branches":0,"n_partial_branches":0,"n_missing_branches":0}}},"z_e9aa84e6767d5a99___init___py":{"hash":"1811d940c10f3dca1417d324f06a1c9a","index":{"url":"z_e9aa84e6767d5a99___init___py.html","file":"src/tmc_driver/com/__init__.py","description":"","nums":{"precision":0,"n_files":1,"n_statements":28,"n_excluded":8,"n_missing":18,"n_branches":0,"n_partial_branches":0,"n_missing_branches":0}}},"z_e9aa84e6767d5a99__tmc_com_py":{"hash":"b52cb323cbc83b5ce9a3ff343af1a260","index":{"url":"z_e9aa84e6767d5a99__tmc_com_py.html","file":"src/tmc_driver/com/_tmc_com.py","description":"","nums":{"precision":0,"n_files":1,"n_statements":38,"n_excluded":43,"n_missing":2,"n_branches":0,"n_partial_branches":0,"n_missing_branches":0}}},"z_e9aa84e6767d5a99__tmc_com_spi_py":{"hash":"61a8cca2d4d82d607e42527e6ddee6c7","index":{"url":"z_e9aa84e6767d5a99__tmc_com_spi_py.html","file":"src/tmc_driver/com/_tmc_com_spi.py","description":"","nums":{"precision":0,"n_files":1,"n_statements":28,"n_excluded":0,"n_missing":7,"n_branches":0,"n_partial_branches":0,"n_missing_branches":0}}},"z_e9aa84e6767d5a99__tmc_com_spi_base_py":{"hash":"d124c33c334c987feb4ed98a07362fba","index":{"url":"z_e9aa84e6767d5a99__tmc_com_spi_base_py.html","file":"src/tmc_driver/com/_tmc_com_spi_base.py","description":"","nums":{"precision":0,"n_files":1,"n_statements":50,"n_excluded":16,"n_missing":13,"n_branches":0,"n_partial_branches":0,"n_missing_branches":0}}},"z_e9aa84e6767d5a99__tmc_com_uart_py":{"hash":"75e99f5a748827b3ecb73a11803f8424","index":{"url":"z_e9aa84e6767d5a99__tmc_com_uart_py.html","file":"src/tmc_driver/com/_tmc_com_uart.py","description":"","nums":{"precision":0,"n_files":1,"n_statements":46,"n_excluded":0,"n_missing":12,"n_branches":0,"n_partial_branches":0,"n_missing_branches":0}}},"z_e9aa84e6767d5a99__tmc_com_uart_base_py":{"hash":"c7b9d31b3b568d7e50313a3ec28ee5c7","index":{"url":"z_e9aa84e6767d5a99__tmc_com_uart_base_py.html","file":"src/tmc_driver/com/_tmc_com_uart_base.py","description":"","nums":{"precision":0,"n_files":1,"n_statements":156,"n_excluded":29,"n_missing":85,"n_branches":0,"n_partial_branches":0,"n_missing_branches":0}}},"z_1bed09767f6f1a1b___init___py":{"hash":"c34063bed6e1e8e027f1066f80991d05","index":{"url":"z_1bed09767f6f1a1b___init___py.html","file":"src/tmc_driver/enable_control/__init__.py","description":"","nums":{"precision":0,"n_files":1,"n_statements":13,"n_excluded":8,"n_missing":3,"n_branches":0,"n_partial_branches":0,"n_missing_branches":0}}},"z_1bed09767f6f1a1b__tmc_ec_py":{"hash":"066259f6d7b0a1cda35a65b0492ef7f0","index":{"url":"z_1bed09767f6f1a1b__tmc_ec_py.html","file":"src/tmc_driver/enable_control/_tmc_ec.py","description":"","nums":{"precision":0,"n_files":1,"n_statements":20,"n_excluded":7,"n_missing":1,"n_branches":0,"n_partial_branches":0,"n_missing_branches":0}}},"z_1bed09767f6f1a1b__tmc_ec_pin_py":{"hash":"a0b214df532773f13e1a0c5a353e4154","index":{"url":"z_1bed09767f6f1a1b__tmc_ec_pin_py.html","file":"src/tmc_driver/enable_control/_tmc_ec_pin.py","description":"","nums":{"precision":0,"n_files":1,"n_statements":26,"n_excluded":0,"n_missing":0,"n_branches":0,"n_partial_branches":0,"n_missing_branches":0}}},"z_1bed09767f6f1a1b__tmc_ec_toff_py":{"hash":"a9ed0433a8b05788fbfdd23b93c1f774","index":{"url":"z_1bed09767f6f1a1b__tmc_ec_toff_py.html","file":"src/tmc_driver/enable_control/_tmc_ec_toff.py","description":"","nums":{"precision":0,"n_files":1,"n_statements":12,"n_excluded":0,"n_missing":0,"n_branches":0,"n_partial_branches":0,"n_missing_branches":0}}},"z_ab4b752bbfa2ed2e___init___py":{"hash":"669090436a5574f186ac2d0096fad97c","index":{"url":"z_ab4b752bbfa2ed2e___init___py.html","file":"src/tmc_driver/motion_control/__init__.py","description":"","nums":{"precision":0,"n_files":1,"n_statements":43,"n_excluded":8,"n_missing":10,"n_branches":0,"n_partial_branches":0,"n_missing_branches":0}}},"z_ab4b752bbfa2ed2e__tmc_mc_py":{"hash":"fff6542f89f45f4aec9bea132a0fa107","index":{"url":"z_ab4b752bbfa2ed2e__tmc_mc_py.html","file":"src/tmc_driver/motion_control/_tmc_mc.py","description":"","nums":{"precision":0,"n_files":1,"n_statements":135,"n_excluded":8,"n_missing":13,"n_branches":0,"n_partial_branches":0,"n_missing_branches":0}}},"z_ab4b752bbfa2ed2e__tmc_mc_int_ramp_generator_py":{"hash":"37346216be2329f12e207fce1426f7b1","index":{"url":"z_ab4b752bbfa2ed2e__tmc_mc_int_ramp_generator_py.html","file":"src/tmc_driver/motion_control/_tmc_mc_int_ramp_generator.py","description":"","nums":{"precision":0,"n_files":1,"n_statements":117,"n_excluded":1,"n_missing":31,"n_branches":0,"n_partial_branches":0,"n_missing_branches":0}}},"z_ab4b752bbfa2ed2e__tmc_mc_step_dir_py":{"hash":"e6fc943daad5ebfe9eee650f963a5703","index":{"url":"z_ab4b752bbfa2ed2e__tmc_mc_step_dir_py.html","file":"src/tmc_driver/motion_control/_tmc_mc_step_dir.py","description":"","nums":{"precision":0,"n_files":1,"n_statements":186,"n_excluded":0,"n_missing":18,"n_branches":0,"n_partial_branches":0,"n_missing_branches":0}}},"z_ab4b752bbfa2ed2e__tmc_mc_step_pwm_dir_py":{"hash":"c393371de33cc726b0e054d980d4e7ce","index":{"url":"z_ab4b752bbfa2ed2e__tmc_mc_step_pwm_dir_py.html","file":"src/tmc_driver/motion_control/_tmc_mc_step_pwm_dir.py","description":"","nums":{"precision":0,"n_files":1,"n_statements":37,"n_excluded":0,"n_missing":6,"n_branches":0,"n_partial_branches":0,"n_missing_branches":0}}},"z_ab4b752bbfa2ed2e__tmc_mc_step_reg_py":{"hash":"5186945f60b79cc788ecba4a7fe1b4c5","index":{"url":"z_ab4b752bbfa2ed2e__tmc_mc_step_reg_py.html","file":"src/tmc_driver/motion_control/_tmc_mc_step_reg.py","description":"","nums":{"precision":0,"n_files":1,"n_statements":17,"n_excluded":0,"n_missing":0,"n_branches":0,"n_partial_branches":0,"n_missing_branches":0}}},"z_ab4b752bbfa2ed2e__tmc_mc_vactual_py":{"hash":"55ea7ab703fbd3050693fe230c070d18","index":{"url":"z_ab4b752bbfa2ed2e__tmc_mc_vactual_py.html","file":"src/tmc_driver/motion_control/_tmc_mc_vactual.py","description":"","nums":{"precision":0,"n_files":1,"n_statements":82,"n_excluded":1,"n_missing":17,"n_branches":0,"n_partial_branches":0,"n_missing_branches":0}}},"z_31b6b07b49f6e852_platform_utils_py":{"hash":"165a365872821cbc779c2d7d291cec7e","index":{"url":"z_31b6b07b49f6e852_platform_utils_py.html","file":"src/tmc_driver/platform_utils.py","description":"","nums":{"precision":0,"n_files":1,"n_statements":14,"n_excluded":0,"n_missing":5,"n_branches":0,"n_partial_branches":0,"n_missing_branches":0}}},"z_2092655fe10236bb__tmc2209_reg_py":{"hash":"84bcfa1956f38f9fcb0c62c042a4a0c0","index":{"url":"z_2092655fe10236bb__tmc2209_reg_py.html","file":"src/tmc_driver/reg/_tmc2209_reg.py","description":"","nums":{"precision":0,"n_files":1,"n_statements":14,"n_excluded":0,"n_missing":0,"n_branches":0,"n_partial_branches":0,"n_missing_branches":0}}},"z_2092655fe10236bb__tmc220x_reg_py":{"hash":"ed70206b717977bec0315a0c255cc52e","index":{"url":"z_2092655fe10236bb__tmc220x_reg_py.html","file":"src/tmc_driver/reg/_tmc220x_reg.py","description":"","nums":{"precision":0,"n_files":1,"n_statements":61,"n_excluded":0,"n_missing":1,"n_branches":0,"n_partial_branches":0,"n_missing_branches":0}}},"z_2092655fe10236bb__tmc224x_reg_py":{"hash":"2c825e4c2a49aa0777cdde0931bc1643","index":{"url":"z_2092655fe10236bb__tmc224x_reg_py.html","file":"src/tmc_driver/reg/_tmc224x_reg.py","description":"","nums":{"precision":0,"n_files":1,"n_statements":98,"n_excluded":0,"n_missing":12,"n_branches":0,"n_partial_branches":0,"n_missing_branches":0}}},"z_2092655fe10236bb__tmc5160_reg_py":{"hash":"9859d28e2259593d1c825027fc437bac","index":{"url":"z_2092655fe10236bb__tmc5160_reg_py.html","file":"src/tmc_driver/reg/_tmc5160_reg.py","description":"","nums":{"precision":0,"n_files":1,"n_statements":121,"n_excluded":0,"n_missing":8,"n_branches":0,"n_partial_branches":0,"n_missing_branches":0}}},"z_2092655fe10236bb__tmc_reg_py":{"hash":"ca908d18cde229620e78bf71729779fb","index":{"url":"z_2092655fe10236bb__tmc_reg_py.html","file":"src/tmc_driver/reg/_tmc_reg.py","description":"","nums":{"precision":0,"n_files":1,"n_statements":98,"n_excluded":0,"n_missing":17,"n_branches":0,"n_partial_branches":0,"n_missing_branches":0}}},"z_2092655fe10236bb__tmc_shared_regs_py":{"hash":"a1fcbff27eae5a9e52c5a973669d2955","index":{"url":"z_2092655fe10236bb__tmc_shared_regs_py.html","file":"src/tmc_driver/reg/_tmc_shared_regs.py","description":"","nums":{"precision":0,"n_files":1,"n_statements":40,"n_excluded":0,"n_missing":0,"n_branches":0,"n_partial_branches":0,"n_missing_branches":0}}},"z_31b6b07b49f6e852_tmc_2208_py":{"hash":"bedac316da484e2117e6110f21a971fe","index":{"url":"z_31b6b07b49f6e852_tmc_2208_py.html","file":"src/tmc_driver/tmc_2208.py","description":"","nums":{"precision":0,"n_files":1,"n_statements":3,"n_excluded":0,"n_missing":0,"n_branches":0,"n_partial_branches":0,"n_missing_branches":0}}},"z_31b6b07b49f6e852_tmc_2209_py":{"hash":"6b4381c2b036d345a670425d81815ac1","index":{"url":"z_31b6b07b49f6e852_tmc_2209_py.html","file":"src/tmc_driver/tmc_2209.py","description":"","nums":{"precision":0,"n_files":1,"n_statements":15,"n_excluded":0,"n_missing":0,"n_branches":0,"n_partial_branches":0,"n_missing_branches":0}}},"z_31b6b07b49f6e852_tmc_220x_py":{"hash":"9cc4cd23bc8ac1f7928082fd47a54ab4","index":{"url":"z_31b6b07b49f6e852_tmc_220x_py.html","file":"src/tmc_driver/tmc_220x.py","description":"","nums":{"precision":0,"n_files":1,"n_statements":124,"n_excluded":0,"n_missing":24,"n_branches":0,"n_partial_branches":0,"n_missing_branches":0}}},"z_31b6b07b49f6e852_tmc_2240_py":{"hash":"b80d17d8b3aa17e48136203afca82463","index":{"url":"z_31b6b07b49f6e852_tmc_2240_py.html","file":"src/tmc_driver/tmc_2240.py","description":"","nums":{"precision":0,"n_files":1,"n_statements":123,"n_excluded":0,"n_missing":17,"n_branches":0,"n_partial_branches":0,"n_missing_branches":0}}},"z_31b6b07b49f6e852_tmc_5160_py":{"hash":"3e329f75c28a3e6032532fc3e19f0640","index":{"url":"z_31b6b07b49f6e852_tmc_5160_py.html","file":"src/tmc_driver/tmc_5160.py","description":"","nums":{"precision":0,"n_files":1,"n_statements":134,"n_excluded":0,"n_missing":25,"n_branches":0,"n_partial_branches":0,"n_missing_branches":0}}},"z_ed420eead8200c62___init___py":{"hash":"22658680d838c6afe38de78655d0aa3e","index":{"url":"z_ed420eead8200c62___init___py.html","file":"src/tmc_driver/tmc_gpio/__init__.py","description":"","nums":{"precision":0,"n_files":1,"n_statements":46,"n_excluded":0,"n_missing":24,"n_branches":0,"n_partial_branches":0,"n_missing_branches":0}}},"z_ed420eead8200c62__tmc_gpio_board_base_py":{"hash":"ebddd949afd9b3929634a1e66bd64e54","index":{"url":"z_ed420eead8200c62__tmc_gpio_board_base_py.html","file":"src/tmc_driver/tmc_gpio/_tmc_gpio_board_base.py","description":"","nums":{"precision":0,"n_files":1,"n_statements":26,"n_excluded":44,"n_missing":0,"n_branches":0,"n_partial_branches":0,"n_missing_branches":0}}},"z_ed420eead8200c62__tmc_gpio_board_gpiozero_py":{"hash":"ae4102f1a7e0739b99ed620f76f3bbdf","index":{"url":"z_ed420eead8200c62__tmc_gpio_board_gpiozero_py.html","file":"src/tmc_driver/tmc_gpio/_tmc_gpio_board_gpiozero.py","description":"","nums":{"precision":0,"n_files":1,"n_statements":72,"n_excluded":0,"n_missing":12,"n_branches":0,"n_partial_branches":0,"n_missing_branches":0}}},"z_ed420eead8200c62__tmc_gpio_board_rpi_gpio_py":{"hash":"75b7ac4706853430949b31cbb6c54bd3","index":{"url":"z_ed420eead8200c62__tmc_gpio_board_rpi_gpio_py.html","file":"src/tmc_driver/tmc_gpio/_tmc_gpio_board_rpi_gpio.py","description":"","nums":{"precision":0,"n_files":1,"n_statements":58,"n_excluded":39,"n_missing":7,"n_branches":0,"n_partial_branches":0,"n_missing_branches":0}}},"z_7a01a19939c8b87c___init___py":{"hash":"2a166a8aefadcfddfcb6ed8c8b625521","index":{"url":"z_7a01a19939c8b87c___init___py.html","file":"src/tmc_driver/tmc_logger/__init__.py","description":"","nums":{"precision":0,"n_files":1,"n_statements":8,"n_excluded":0,"n_missing":1,"n_branches":0,"n_partial_branches":0,"n_missing_branches":0}}},"z_7a01a19939c8b87c__tmc_logger_base_py":{"hash":"3041aabade941dfe41c3980172766b1e","index":{"url":"z_7a01a19939c8b87c__tmc_logger_base_py.html","file":"src/tmc_driver/tmc_logger/_tmc_logger_base.py","description":"","nums":{"precision":0,"n_files":1,"n_statements":28,"n_excluded":37,"n_missing":5,"n_branches":0,"n_partial_branches":0,"n_missing_branches":0}}},"z_7a01a19939c8b87c__tmc_logger_cpython_py":{"hash":"b457e871557d70212b080761716d9574","index":{"url":"z_7a01a19939c8b87c__tmc_logger_cpython_py.html","file":"src/tmc_driver/tmc_logger/_tmc_logger_cpython.py","description":"","nums":{"precision":0,"n_files":1,"n_statements":67,"n_excluded":0,"n_missing":14,"n_branches":0,"n_partial_branches":0,"n_missing_branches":0}}}}}